poselab/__init__.py
poselab/filter.py
poselab/pose.py
poselab/poseparser.py
poselab/visual.py
poselab-0.2.2.dist-info/LICENSE
poselab-0.2.2.dist-info/METADATA
poselab-0.2.2.dist-info/WHEEL
poselab-0.2.2.dist-info/top_level.txt
poselab-0.2.2.dist-info/RECORD
