Metadata-Version: 2.1
Name: poselab
Version: 0.2.2
Summary: A colmap pose analysis, filter and visualization toolkit
Author-email: yoavalon <algoretics@gmail.com>
Project-URL: Homepage, https://github.com/yoavalon/poselab
Project-URL: Issues, https://github.com/yoavalon/poselab/issues
Classifier: Programming Language :: Python :: 3
Classifier: License :: OSI Approved :: MIT License
Classifier: Operating System :: OS Independent
Requires-Python: >=3.8
License-File: LICENSE
